oarelatedworkevaluator/__init__.py
oarelatedworkevaluator/__main__.py
oarelatedworkevaluator/workflow.py
oarelatedworkevaluator/datasets/__init__.py
oarelatedworkevaluator/datasets/oa_related_work.py
oarelatedworkevaluator/etl/__init__.py
oarelatedworkevaluator/etl/dataset.py
oarelatedworkevaluator/etl/sample.py
oarelatedworkevaluator/etl/data_structures/__init__.py
oarelatedworkevaluator/etl/data_structures/structured_document.py
oarelatedworkevaluator/evaluation/__init__.py
oarelatedworkevaluator/evaluation/evaluator.py
oarelatedworkevaluator/evaluation/utils.py
oarelatedworkevaluator/metrics/__init__.py
oarelatedworkevaluator/metrics/bertscorehfwrapper/__init__.py
oarelatedworkevaluator/metrics/bertscorehfwrapper/bert_score.py
oarelatedworkevaluator/metrics/blockmatching/__init__.py
oarelatedworkevaluator/metrics/blockmatching/block_matching.py
oarelatedworkevaluator/metrics/huggingfacerouge/__init__.py
oarelatedworkevaluator/metrics/huggingfacerouge/app.py
oarelatedworkevaluator/metrics/huggingfacerouge/rouge.py
oarelatedworkevaluator/metrics/intextcitations/__init__.py
oarelatedworkevaluator/metrics/intextcitations/in_text_citations.py
oarelatedworkevaluator/results/__init__.py
oarelatedworkevaluator/results/result.py
oarelatedworkevaluator/results/results_reader.py
oarelatedworkevaluator/utils/__init__.py
oarelatedworkevaluator/utils/general_entities.py
oarelatedworkevaluator-1.0.0.dist-info/METADATA
oarelatedworkevaluator-1.0.0.dist-info/WHEEL
oarelatedworkevaluator-1.0.0.dist-info/top_level.txt
oarelatedworkevaluator-1.0.0.dist-info/RECORD
