Metadata-Version: 2.1
Name: oarelatedworkevaluator
Version: 1.0.0
Summary: Package for evaluation of OARelatedWork dataset.
Home-page: https://github.com/KNOT-FIT-BUT/OARelatedWorkEvaluator
Author: Martin Dočekal
License: The Unlicense
Keywords: dataset,OARelatedWork evaluation,OARelatedWork dataset
Requires-Python: >=3.10
Requires-Dist: classconfig
Requires-Dist: datasets
Requires-Dist: torch
Requires-Dist: evaluate
Requires-Dist: bert-score ~=0.3.13
Requires-Dist: munkres ~=1.1.4
Requires-Dist: absl-py
Requires-Dist: nltk
Requires-Dist: rouge-score >=0.1.2
